xorq/__init__.py
xorq/api.py
xorq/catalog.py
xorq/cli.py
xorq/config.py
xorq/conftest.py
xorq/init_templates.py
xorq/internal.py
xorq/loader.py
xorq/ml.py
xorq/udf.py
xorq/backends/__init__.py
xorq/backends/conftest.py
xorq/backends/datafusion/__init__.py
xorq/backends/datafusion/tests/__init__.py
xorq/backends/datafusion/tests/conftest.py
xorq/backends/datafusion/tests/test_cache.py
xorq/backends/datafusion/tests/test_udwf.py
xorq/backends/duckdb/__init__.py
xorq/backends/duckdb/tests/__init__.py
xorq/backends/duckdb/tests/conftest.py
xorq/backends/duckdb/tests/test_asof_join.py
xorq/backends/duckdb/tests/test_basic.py
xorq/backends/pandas/__init__.py
xorq/backends/pandas/convert.py
xorq/backends/pandas/executor.py
xorq/backends/pandas/helpers.py
xorq/backends/pandas/kernels.py
xorq/backends/pandas/rewrites.py
xorq/backends/pandas/udf.py
xorq/backends/pandas/tests/__init__.py
xorq/backends/pandas/tests/conftest.py
xorq/backends/pandas/tests/test_arrays.py
xorq/backends/pandas/tests/test_caching.py
xorq/backends/pandas/tests/test_cast.py
xorq/backends/pandas/tests/test_client.py
xorq/backends/pandas/tests/test_core.py
xorq/backends/pandas/tests/test_format.py
xorq/backends/pandas/tests/test_functions.py
xorq/backends/pandas/tests/test_helpers.py
xorq/backends/pandas/tests/test_join.py
xorq/backends/pandas/tests/test_maps.py
xorq/backends/pandas/tests/test_operations.py
xorq/backends/pandas/tests/test_ops.py
xorq/backends/pandas/tests/test_strings.py
xorq/backends/pandas/tests/test_structs.py
xorq/backends/pandas/tests/test_temporal.py
xorq/backends/pandas/tests/test_udf.py
xorq/backends/pandas/tests/test_window.py
xorq/backends/postgres/__init__.py
xorq/backends/postgres/compiler.py
xorq/backends/postgres/tests/conftest.py
xorq/backends/postgres/tests/test_cache.py
xorq/backends/postgres/tests/test_read.py
xorq/backends/pyiceberg/__init__.py
xorq/backends/pyiceberg/compiler.py
xorq/backends/pyiceberg/relations.py
xorq/backends/pyiceberg/tests/__init__.py
xorq-0.3.7.dist-info/METADATA
xorq-0.3.7.dist-info/WHEEL
xorq-0.3.7.dist-info/entry_points.txt
xorq-0.3.7.dist-info/licenses/LICENSE
xorq-0.3.7.dist-info/RECORD
