Metadata-Version: 2.4
Name: xorq
Version: 0.3.7
Summary: Data processing library built on top of Ibis and DataFusion to write multi-engine data workflows.
Project-URL: Homepage, https://www.xorq.dev/
Project-URL: Repository, https://github.com/xorq-labs/xorq/
Project-URL: Issues, https://github.com/xorq-labs/xorq/issues
Project-URL: Changelog, https://github.com/xorq-labs/xorq/blob/main/CHANGELOG.md
Project-URL: Documentation, https://docs.xorq.dev/
Author-email: Hussain Sultan <hussain@letsql.com>
Maintainer-email: Dan Lovell <dan@letsql.com>, Daniel Mesejo <mesejo@letsql.com>
License:                                  Apache License
License-File: LICENSE
Classifier: Development Status :: 3 - Alpha
Classifier: Intended Audience :: Developers
Classifier: Intended Audience :: Science/Research
Classifier: License :: OSI Approved :: Apache Software License
Classifier: Programming Language :: Python :: Implementation :: CPython
Classifier: Programming Language :: Rust
Classifier: Topic :: Database :: Database Engines/Servers
Classifier: Topic :: Software Development :: User Interfaces
Requires-Python: >=3.10
Requires-Dist: atpublic>=5.1
Requires-Dist: attrs<26,>=24.0.0; python_version >= '3.10' and python_version < '4.0'
Requires-Dist: cityhash<1,>=0.4.7; python_version >= '3.10' and python_version < '4.0'
Requires-Dist: cloudpickle>=3.1.1
Requires-Dist: cryptography>=45.0.3
Requires-Dist: dask==2025.1.0; python_version >= '3.10' and python_version < '4.0'
Requires-Dist: envyaml>=1.10.211231
Requires-Dist: geoarrow-types<1,>=0.2; python_version >= '3.10' and python_version < '4.0'
Requires-Dist: opentelemetry-exporter-otlp>=1.32.1
Requires-Dist: opentelemetry-exporter-prometheus>=0.55b1
Requires-Dist: opentelemetry-sdk>=1.32.1
Requires-Dist: pandas<3,>=1.5.3; python_version >= '3.10' and python_version < '4.0'
Requires-Dist: parsy>=2
Requires-Dist: prometheus-client>=0.22.1
Requires-Dist: pyarrow-hotfix<1,>=0.4; python_version >= '3.10' and python_version < '4.0'
Requires-Dist: pyarrow<22,>=13.0.0; python_version >= '3.10' and python_version < '4.0'
Requires-Dist: pytest-mock<4,>=3.14.0; python_version >= '3.10' and python_version < '4.0'
Requires-Dist: python-dateutil>=2.8.2
Requires-Dist: pythran>=0.17.0; sys_platform == 'darwin'
Requires-Dist: pytz>=2022.7
Requires-Dist: pyyaml>=6.0.2
Requires-Dist: rich>=13.9.4
Requires-Dist: sqlglot!=26.32.0,>=23.4
Requires-Dist: strenum>=0.4.15; python_version <= '3.10'
Requires-Dist: structlog<26,>=24.2.0; python_version >= '3.10' and python_version < '4.0'
Requires-Dist: toolz>=0.11
Requires-Dist: typing-extensions>=4.3.0
Requires-Dist: uv>=0.7.20
Requires-Dist: xorq-datafusion==0.2.5
Provides-Extra: datafusion
Requires-Dist: datafusion<49,>=0.6; (python_version >= '3.10' and python_version < '4.0') and extra == 'datafusion'
Provides-Extra: duckdb
Requires-Dist: duckdb>=1.1.3; extra == 'duckdb'
Provides-Extra: examples
Requires-Dist: adbc-driver-postgresql>=1.4.0; extra == 'examples'
Requires-Dist: duckdb<2,>=0.10.3; (python_version >= '3.10' and python_version < '4.0') and extra == 'examples'
Requires-Dist: fsspec<2025.10.1,>=2024.6.1; (python_version >= '3.10' and python_version < '4.0') and extra == 'examples'
Requires-Dist: mcp>=1.5.0; extra == 'examples'
Requires-Dist: openai>=1.65.4; extra == 'examples'
Requires-Dist: pins[gcs]<1,>=0.8.3; (python_version >= '3.10' and python_version < '4.0') and extra == 'examples'
Requires-Dist: quickgrove>=0.1.2; extra == 'examples'
Requires-Dist: requests>=2.32.3; extra == 'examples'
Requires-Dist: scikit-learn<2.0.0,>=1.4.0; extra == 'examples'
Requires-Dist: xgboost>=1.6.1; (python_version >= '3.10' and python_version < '4.0') and extra == 'examples'
Requires-Dist: xorq-feature-utils; extra == 'examples'
Requires-Dist: xorq-weather-lib; extra == 'examples'
Provides-Extra: ibis
Requires-Dist: ibis-framework>=10.5.0; extra == 'ibis'
Provides-Extra: postgres
Requires-Dist: adbc-driver-postgresql>=1.4.0; extra == 'postgres'
Requires-Dist: psycopg[binary]>=3.2.0; extra == 'postgres'
Provides-Extra: pyiceberg
Requires-Dist: pyiceberg[sql-postgres,sql-sqlite]>=0.9.0; extra == 'pyiceberg'
Provides-Extra: quickgrove
Requires-Dist: quickgrove>=0.1.2; extra == 'quickgrove'
Provides-Extra: snowflake
Requires-Dist: adbc-driver-snowflake>=1.5.0; extra == 'snowflake'
Requires-Dist: snowflake-connector-python<4,>=3.10.1; (python_version >= '3.10' and python_version < '4.0') and extra == 'snowflake'
Provides-Extra: sqlite
Requires-Dist: adbc-driver-sqlite>=1.4.0; extra == 'sqlite'
